Workbook

Sheet Orders
A1: Row ID | B1: Order ID | C1: Order Date | D1: Ship Date | E1: Ship Mode | F1: Customer ID | G1: Customer Name | H1: Segment | I1: Country | J1: City | K1: State | L1: Region | M1: Product ID | N1: Category | O1: Sub-Category | P1: Product Name | Q1: Sales | R1: Quantity | S1: Profit | T1: Category Manager | U1: Category Manager2 | V1: Profit Status(Kar Durumu)
A2: 1 | B2: CA-2019-152156 | C2: 43777 | D2: 43780 | E2: Second Class | F2: CG-12520 | G2: Claire Gute | H2: Consumer | I2: United States | J2: Henderson | K2: Kentucky | L2: South | M2: FUR-BO-10001798 | N2: Furniture | O2: Bookcases | P2: Bush Somerset Collection Bookcase | Q2: 261.96 | R2: 2 | S2: 41.9136 | T2: =VLOOKUP(N2,Referans!A:B,2,FALSE) -> Ahmet Yılmaz | U2: =INDEX(Referans!B:B,MATCH(N2,Referans!A:A,0)) -> Ahmet Yılmaz | V2: =IF(S2>0,"KARLI",IF(S2=0,"KAR VEYA ZARAR YOK","ZARARLI")) -> KARLI
A3: 2 | B3: CA-2019-152156 | C3: 43777 | D3: 43780 | E3: Second Class | F3: CG-12520 | G3: Claire Gute | H3: Consumer | I3: United States | J3: Henderson | K3: Kentucky | L3: South | M3: FUR-CH-10000454 | N3: Furniture | O3: Chairs | P3: Hon Deluxe Fabric Upholstered Stacking Chairs, Rounded Back | Q3: 731.94 | R3: 3 | S3: 219.582 | T3: =VLOOKUP(N3,Referans!A:B,2,FALSE) -> Ahmet Yılmaz | U3: =INDEX(Referans!B:B,MATCH(N3,Referans!A:A,0)) -> Ahmet Yılmaz | V3: =IF(S3>0,"KARLI",IF(S3=0,"KAR VEYA ZARAR YOK","ZARARLI")) -> KARLI
A4: 3 | B4: CA-2019-138688 | C4: 43628 | D4: 43632 | E4: Second Class | F4: DV-13045 | G4: Darrin Van Huff | H4: Corporate | I4: United States | J4: Los Angeles | K4: California | L4: West | M4: OFF-LA-10000240 | N4: Office Supplies | O4: Labels | P4: Self-Adhesive Address Labels for Typewriters by Universal | Q4: 14.62 | R4: 2 | S4: 6.8714 | T4: =VLOOKUP(N4,Referans!A:B,2,FALSE) -> Ayşe Demir | U4: =INDEX(Referans!B:B,MATCH(N4,Referans!A:A,0)) -> Ayşe Demir | V4: =IF(S4>0,"KARLI",IF(S4=0,"KAR VEYA ZARAR YOK","ZARARLI")) -> KARLI
A5: 13 | B5: CA-2020-114412 | C5: 43936 | D5: 43941 | E5: Standard Class | F5: AA-10480 | G5: Andrew Allen | H5: Consumer | I5: United States | J5: Concord | K5: North Carolina | L5: South | M5: OFF-PA-10002365 | N5: Office Supplies | O5: Paper | P5: Xerox 1967 | Q5: 15.552 | R5: 3 | S5: 5.4432 | T5: =VLOOKUP(N5,Referans!A:B,2,FALSE) -> Ayşe Demir | U5: =INDEX(Referans!B:B,MATCH(N5,Referans!A:A,0)) -> Ayşe Demir | V5: =IF(S5>0,"KARLI",IF(S5=0,"KAR VEYA ZARAR YOK","ZARARLI")) -> KARLI
A6: 14 | B6: CA-2019-161389 | C6: 43804 | D6: 43809 | E6: Standard Class | F6: IM-15070 | G6: Irene Maddox | H6: Consumer | I6: United States | J6: Seattle | K6: Washington | L6: West | M6: OFF-BI-10003656 | N6: Office Supplies | O6: Binders | P6: Fellowes PB200 Plastic Comb Binding Machine | Q6: 407.976 | R6: 3 | S6: 132.5922 | T6: =VLOOKUP(N6,Referans!A:B,2,FALSE) -> Ayşe Demir | U6: =INDEX(Referans!B:B,MATCH(N6,Referans!A:A,0)) -> Ayşe Demir | V6: =IF(S6>0,"KARLI",IF(S6=0,"KAR VEYA ZARAR YOK","ZARARLI")) -> KARLI
A7: 22 | B7: CA-2019-137330 | C7: 43808 | D7: 43812 | E7: Standard Class | F7: KB-16585 | G7: Ken Black | H7: Corporate | I7: United States | J7: Fremont | K7: Nebraska | L7: Central | M7: OFF-AR-10000246 | N7: Office Supplies | O7: Art | P7: Newell 318 | Q7: 19.46 | R7: 7 | S7: 5.0596 | T7: =VLOOKUP(N7,Referans!A:B,2,FALSE) -> Ayşe Demir | U7: =INDEX(Referans!B:B,MATCH(N7,Referans!A:A,0)) -> Ayşe Demir | V7: =IF(S7>0,"KARLI",IF(S7=0,"KAR VEYA ZARAR YOK","ZARARLI")) -> KARLI
A8: 23 | B8: CA-2019-137330 | C8: 43808 | D8: 43812 | E8: Standard Class | F8: KB-16585 | G8: Ken Black | H8: Corporate | I8: United States | J8: Fremont | K8: Nebraska | L8: Central | M8: OFF-AP-10001492 | N8: Office Supplies | O8: Appliances | P8: Acco Six-Outlet Power Strip, 4' Cord Length | Q8: 60.34 | R8: 7 | S8: 15.6884 | T8: =VLOOKUP(N8,Referans!A:B,2,FALSE) -> Ayşe Demir | U8: =INDEX(Referans!B:B,MATCH(N8,Referans!A:A,0)) -> Ayşe Demir | V8: =IF(S8>0,"KARLI",IF(S8=0,"KAR VEYA ZARAR YOK","ZARARLI")) -> KARLI
A9: 24 | B9: US-2020-156909 | C9: 44028 | D9: 44030 | E9: Second Class | F9: SF-20065 | G9: Sandra Flanagan | H9: Consumer | I9: United States | J9: Philadelphia | K9: Pennsylvania | L9: East | M9: FUR-CH-10002774 | N9: Furniture | O9: Chairs | P9: Global Deluxe Stacking Chair, Gray | Q9: 71.372 | R9: 2 | S9: -1.0196 | T9: =VLOOKUP(N9,Referans!A:B,2,FALSE) -> Ahmet Yılmaz | U9: =INDEX(Referans!B:B,MATCH(N9,Referans!A:A,0)) -> Ahmet Yılmaz | V9: =IF(S9>0,"KARLI",IF(S9=0,"KAR VEYA ZARAR YOK","ZARARLI")) -> ZARARLI
A10: 26 | B10: CA-2019-121755 | C10: 43481 | D10: 43485 | E10: Second Class | F10: EH-13945 | G10: Eric Hoffmann | H10: Consumer | I10: United States | J10: Los Angeles | K10: California | L10: West | M10: OFF-BI-10001634 | N10: Office Supplies | O10: Binders | P10: Wilson Jones Active Use Binders | Q10: 11.648 | R10: 2 | S10: 4.2224 | T10: =VLOOKUP(N10,Referans!A:B,2,FALSE) -> Ayşe Demir | U10: =INDEX(Referans!B:B,MATCH(N10,Referans!A:A,0)) -> Ayşe Demir | V10: =IF(S10>0,"KARLI",IF(S10=0,"KAR VEYA ZARAR YOK","ZARARLI")) -> KARLI
A11: 27 | B11: CA-2019-121755 | C11: 43481 | D11: 43485 | E11: Second Class | F11: EH-13945 | G11: Eric Hoffmann | H11: Consumer | I11: United States | J11: Los Angeles | K11: California | L11: West | M11: TEC-AC-10003027 | N11: Technology | O11: Accessories | P11: Imation 8GB Mini TravelDrive USB 2.0 Flash Drive | Q11: 90.57 | R11: 3 | S11: 11.7741 | T11: =VLOOKUP(N11,Referans!A:B,2,FALSE) -> Mehmet Kaya | U11: =INDEX(Referans!B:B,MATCH(N11,Referans!A:A,0)) -> Mehmet Kaya | V11: =IF(S11>0,"KARLI",IF(S11=0,"KAR VEYA ZARAR YOK","ZARARLI")) -> KARLI
A12: 35 | B12: CA-2020-107727 | C12: 44123 | D12: 44127 | E12: Second Class | F12: MA-17560 | G12: Matt Abelman | H12: Home Office | I12: United States | J12: Houston | K12: Texas | L12: Central | M12: OFF-PA-10000249 | N12: Office Supplies | O12: Paper | P12: Easy-staple paper | Q12: 29.472 | R12: 3 | S12: 9.9468 | T12: =VLOOKUP(N12,Referans!A:B,2,FALSE) -> Ayşe Demir | U12: =INDEX(Referans!B:B,MATCH(N12,Referans!A:A,0)) -> Ayşe Demir | V12: =IF(S12>0,"KARLI",IF(S12=0,"KAR VEYA ZARAR YOK","ZARARLI")) -> KARLI
A13: 36 | B13: CA-2019-117590 | C13: 43807 | D13: 43809 | E13: First Class | F13: GH-14485 | G13: Gene Hale | H13: Corporate | I13: United States | J13: Richardson | K13: Texas | L13: Central | M13: TEC-PH-10004977 | N13: Technology | O13: Phones | P13: GE 30524EE4 | Q13: 1097.544 | R13: 7 | S13: 123.4737 | T13: =VLOOKUP(N13,Referans!A:B,2,FALSE) -> Mehmet Kaya | U13: =INDEX(Referans!B:B,MATCH(N13,Referans!A:A,0)) -> Mehmet Kaya | V13: =IF(S13>0,"KARLI",IF(S13=0,"KAR VEYA ZARAR YOK","ZARARLI")) -> KARLI
... A5900: 9994 | B5900: CA-2020-119914 | C5900: 43955 | D5900: 43960 | E5900: Second Class | F5900: CC-12220 | G5900: Chris Cortes | H5900: Consumer | I5900: United States | J5900: Westminster | K5900: California | L5900: West | M5900: OFF-AP-10002684 | N5900: Office Supplies | O5900: Appliances | P5900: Acco 7-Outlet Masterpiece Power Center, Wihtout Fax/Phone Line Protection | Q5900: 243.16 | R5900: 2 | S5900: 72.948 | T5900: =VLOOKUP(N5900,Referans!A:B,2,FALSE) -> Ayşe Demir | U5900: =INDEX(Referans!B:B,MATCH(N5900,Referans!A:A,0)) -> Ayşe Demir | V5900: =IF(S5900>0,"KARLI",IF(S5900=0,"KAR VEYA ZARAR YOK","ZARARLI")) -> KARLI

Sheet Returns
A1: Returned | B1: Order ID
A2: Yes | B2: CA-2015-100762
A3: Yes | B3: CA-2015-100762
A4: Yes | B4: CA-2015-100762
A5: Yes | B5: CA-2015-100762
A6: Yes | B6: CA-2015-100867
A7: Yes | B7: CA-2015-102652
A8: Yes | B8: CA-2015-102652
A9: Yes | B9: CA-2015-102652
A10: Yes | B10: CA-2015-102652
A11: Yes | B11: CA-2015-103373
A12: Yes | B12: CA-2015-103744
... A801: Yes | B801: US-2018-155999

Sheet Referans
A1: Category | B1: Category Manager
A2: Furniture | B2: Ahmet Yılmaz
A3: Office Supplies | B3: Ayşe Demir
A4: Technology | B4: Mehmet Kaya

Sheet Notes
A1: Kontrol | B1: Sonuç | C1: Yapılan İşlem
A2: Boş Satırlar | B2: Bulunamadı | C2: İşlem yapılmadı | D2: **yinelenen sipariş numaraları ve ona ait ürün numaraları turuncuya boyanmıştır.**Order ID aynı çünkü tek bir sipariş.Product ID farklı çünkü müşteri aynı siparişte iki veya daha fazla farklı ürün satın almış.Bu nedenle bu kayıtlar duplicate (yinelenen kayıt) değildir.
A3: Order ID Tekrarları | B3: Tekrar eden sipariş ID'ler bulundu. | C3: Aynı siparişe ait farklı ürünler olduğu doğrulandı, kayıtlar silinmedi. | D3: 1.Ne analiz ettik? 2.Ne bulduk? 3.Şirket bu bilgiyle ne yapabilir?
A4: Veri tipleri | B4: Kontrol edildi | C4: Sales, Profit, Quantity ve Discount sayısal olarak doğrulandı. Değerler sayıya dönüştürüldü ve 1000 ayırıcısı kullanıldı. | D4: Her Analizde yukarıdaki 3 soruyu sorup cevaplayacağız.
A5: Tarih | B5: Kontrol edildi | C5: Tarih formatında girilmiş.

Sheet Notes 2
A2: Technology kategorisinde kaç ürün satırı olduğunu bulmak | B2: =COUNTIF(Orders!N:N,"Technology") -> 1083
A3: Technology kategorisinin toplam satışını bulmak | B3: =SUMIF(Orders!N:N,"Technology",Orders!Q:Q) -> 498094.99
A4: Consumer segmentinin toplam satışını hesaplamak | B4: =SUMIF(Orders!H:H,"Consumer",Orders!Q:Q) -> 628768.6

Sheet Dashboard
A1: SUPERSTORE SALES DASHBOARD
A2: Toplam Satış | E2: Toplam Kar | H2: Toplam Müşteri | L2: Toplam Sipariş
B3: =SUM(Orders!Q:Q) -> 1342420.9 | F3: =SUM(Orders!S:S) -> 175234.44 | I3: =ROWS(_xlfn.UNIQUE(Table1[Customer ID])) -> 773 | M3: =ROWS(_xlfn.UNIQUE(Table1[Order ID])) -> 3002

Sheet Pivot 1
A1: Bölge Analizi
A3: Satır Etiketleri | B3: Toplam Sales | C3: Toplam Profit
A4: West | B4: 437608.54 | C4: 67860.563
A5: East | B5: 393768.73 | C5: 53372.157
A6: Central | B6: 294527.5 | C6: 27450.007
A7: South | B7: 216516.08 | C7: 26551.716
A8: Genel Toplam | B8: 1342420.9 | C8: 175234.44

Sheet Pivot 2
A1: Kategori Analizi
A3: Satır Etiketleri | B3: Toplam Sales | C3: Toplam Profit
A4: Technology | B4: 498094.99 | C4: 90458.249
A5: Office Supplies | B5: 430037.16 | C5: 74797.851
A6: Furniture | B6: 414288.71 | C6: 9978.3444
A7: Genel Toplam | B7: 1342420.9 | C7: 175234.44

Sheet Pivot 3
A1: Alt Kategori Analizi
A3: Satır Etiketleri | B3: Toplam Sales | C3: Toplam Profit
A4: Phones | B4: 184302.55 | C4: 22308.918
A5: Chairs | B5: 179473 | C5: 13406.703
A6: Storage | B6: 128466.32 | C6: 13607.087
A7: Binders | B7: 122471.37 | C7: 17885.376
A8: Tables | B8: 121726.74 | C8: -11091.637
A9: Copiers | B9: 112498.8 | C9: 42774.583
A10: Accessories | B10: 101842.09 | C10: 25336.645
A11: Machines | B11: 99451.561 | C11: 38.1024
A12: Appliances | B12: 68977.247 | C12: 13166.61
A13: Furnishings | B13: 56789.218 | C13: 8034.4328
A14: Bookcases | B14: 56299.746 | C14: -371.1551
A15: Paper | B15: 48356.612 | C15: 21112.378
... A21: Genel Toplam | B21: 1342420.9 | C21: 175234.44

Sheet Pivot 4
A1: Segment Analizi
A3: Satır Etiketleri | B3: Toplam Sales | C3: Toplam Profit
A4: Consumer | B4: 628768.6 | C4: 81339.192
A5: Corporate | B5: 448954.19 | C5: 57777.532
A6: Home Office | B6: 264698.07 | C6: 36117.719
A7: Genel Toplam | B7: 1342420.9 | C7: 175234.44

Sheet Pivot 5
A1: Müşteri Analizi
A3: Satır Etiketleri | B3: Toplam Sales | C3: Toplam Profit
A4: Tamara Chand | B4: 18344.052 | C4: 8764.9483
A5: Raymond Buch | B5: 15117.339 | C5: 6976.0959
A6: Tom Ashbrook | B6: 13807.77 | C6: 4523.3625
A7: Adrian Barton | B7: 12694.909 | C7: 5088.9448
A8: Christopher Conant | B8: 12129.072 | C8: 2177.0493
A9: Sanjit Engle | B9: 11424.978 | C9: 2436.9525
A10: Caroline Jumper | B10: 11164.974 | C10: 858.7414
A11: Hunter Lopez | B11: 10979.108 | C11: 5174.3968
A12: Karen Ferguson | B12: 9999.274 | C12: 1577.6134
A13: Seth Vernon | B13: 9501.148 | C13: 1610.002
A14: Edward Hooks | B14: 9318.988 | C14: 1164.6312
A15: Helen Wasserman | B15: 9257.934 | C15: 2146.9635
... A777: Genel Toplam | B777: 1342420.9 | C777: 175234.44

Sheet Pivot 6
A1: Ürün Analizi
A3: Satır Etiketleri | B3: Toplam Sales | C3: Toplam Profit
A4: Canon imageCLASS 2200 Advanced Copier | B4: 61599.824 | C4: 25199.928
A5: Hewlett Packard LaserJet 3310 Copier | B5: 16079.732 | C5: 6407.8932
A6: 3D Systems Cube Printer, 2nd Generation, Magenta | B6: 14299.89 | C6: 3717.9714
A7: GBC Ibimaster 500 Manual ProClick Binding System | B7: 13621.542 | C7: 1826.352
A8: GBC DocuBind TL300 Electric Binding System | B8: 12737.258 | C8: 2753.7593
A9: GBC DocuBind P400 Electric Binding System | B9: 12521.108 | C9: 762.1544
A10: Samsung Galaxy Mega 6.3 | B10: 12263.708 | C10: 1696.7596
A11: HON 5400 Series Task Chairs for Big and Tall | B11: 11846.562 | C11: 70.098
A12: Martin Yale Chadless Opener Electric Letter Opener | B12: 11825.902 | C12: -1232.5588
A13: Global Troy Executive Leather Low-Back Tilter | B13: 10169.894 | C13: 776.519
A14: Fellowes PB500 Electric Punch Plastic Comb Binding Machine with Manual Bind | B14: 9659.524 | C14: -508.396
A15: Cubify CubeX 3D Printer Double Head Print | B15: 9299.969 | C15: -6239.9792
... A1746: Genel Toplam | B1746: 1342420.9 | C1746: 175234.44

Sheet Pivot 7
A1: Zaman Analizi
A3: Satır Etiketleri | B3: Toplam Sales | C3: Toplam Profit
A4: 2019 | B4: 609205.6 | C4: 81795.174
A5: 2020 | B5: 733215.26 | C5: 93439.27
A6: Genel Toplam | B6: 1342420.9 | C6: 175234.44

Sheet Pivot 8
A1: Eyalet Analizi
A3: Satır Etiketleri | B3: Toplam Sales | C3: Toplam Profit
A4: California | B4: 277940.26 | C4: 49372.175
A5: New York | B5: 165767.1 | C5: 41012.021
A6: Washington | B6: 85354.18 | C6: 21466.655
A7: Texas | B7: 85107.91 | C7: -14078.16
A8: Pennsylvania | B8: 75754.95 | C8: -9297.7975
A9: Michigan | B9: 53253.684 | C9: 17480.281
A10: Ohio | B10: 48012.86 | C10: -9339.4223
A11: Illinois | B11: 45385.33 | C11: -9554.6539
A12: Indiana | B12: 43978.23 | C12: 15524.66
A13: Florida | B13: 40047.999 | C13: -227.7465
A14: North Carolina | B14: 38424.125 | C14: -4827.6923
A15: Virginia | B15: 34291.25 | C15: 9657.4876
... A53: Genel Toplam | B53: 1342420.9 | C53: 175234.44

Sheet Pivot 9
A3: Satır Etiketleri | B3: Toplam Sales
A4: Furniture | B4: 414288.71
A5: Office Supplies | B5: 430037.16
A6: Technology | B6: 498094.99
A7: Genel Toplam | B7: 1342420.9

Sheet Pivot 10
A3: Satır Etiketleri | B3: Toplam Sales
A4: Phones | B4: 184302.55
A5: Chairs | B5: 179473
A6: Storage | B6: 128466.32
A7: Binders | B7: 122471.37
A8: Tables | B8: 121726.74
A9: Copiers | B9: 112498.8
A10: Accessories | B10: 101842.09
A11: Machines | B11: 99451.561
A12: Appliances | B12: 68977.247
A13: Furnishings | B13: 56789.218
A14: Genel Toplam | B14: 1175998.9

Sheet Pivot 11
A3: Satır Etiketleri | B3: Toplam Sales
A4: Consumer | B4: 628768.6
A5: Corporate | B5: 448954.19
A6: Home Office | B6: 264698.07
A7: Genel Toplam | B7: 1342420.9

Sheet Pivot 12
A3: Satır Etiketleri | B3: Toplam Sales
A4: Canon imageCLASS 2200 Advanced Copier | B4: 61599.824
A5: Hewlett Packard LaserJet 3310 Copier | B5: 16079.732
A6: 3D Systems Cube Printer, 2nd Generation, Magenta | B6: 14299.89
A7: GBC Ibimaster 500 Manual ProClick Binding System | B7: 13621.542
A8: GBC DocuBind TL300 Electric Binding System | B8: 12737.258
A9: GBC DocuBind P400 Electric Binding System | B9: 12521.108
A10: Samsung Galaxy Mega 6.3 | B10: 12263.708
A11: HON 5400 Series Task Chairs for Big and Tall | B11: 11846.562
A12: Martin Yale Chadless Opener Electric Letter Opener | B12: 11825.902
A13: Global Troy Executive Leather Low-Back Tilter | B13: 10169.894
A14: Genel Toplam | B14: 176965.42

Sheet Pivot 13
A3: Satır Etiketleri | B3: Toplam Sales
A4: Tamara Chand | B4: 18344.052
A5: Raymond Buch | B5: 15117.339
A6: Tom Ashbrook | B6: 13807.77
A7: Adrian Barton | B7: 12694.909
A8: Christopher Conant | B8: 12129.072
A9: Sanjit Engle | B9: 11424.978
A10: Caroline Jumper | B10: 11164.974
A11: Hunter Lopez | B11: 10979.108
A12: Karen Ferguson | B12: 9999.274
A13: Seth Vernon | B13: 9501.148
A14: Genel Toplam | B14: 125162.62
